{
    "className": "org.joget.apps.form.model.Form",
    "elements": [
        {
            "className": "org.joget.apps.form.model.Section",
            "elements": [
                {
                    "className": "org.joget.apps.form.model.Column",
                    "elements": [
                        {
                            "className": "org.joget.apps.form.lib.TextField",
                            "properties": {
                                "encryption": "",
                                "id": "incident",
                                "label": "Incident",
                                "maxlength": "",
                                "placeholder": "",
                                "readonly": "",
                                "readonlyLabel": "",
                                "size": "",
                                "storeNumeric": "",
                                "style": "",
                                "validator": {
                                    "className": "",
                                    "properties": {}
                                },
                                "value": "",
                                "workflowVariable": ""
                            }
                        },
                        {
                            "className": "org.joget.apps.form.lib.TextField",
                            "properties": {
                                "encryption": "",
                                "id": "actual_solution",
                                "label": "Actual Solution",
                                "maxlength": "",
                                "placeholder": "",
                                "readonly": "",
                                "readonlyLabel": "",
                                "size": "",
                                "storeNumeric": "",
                                "style": "",
                                "validator": {
                                    "className": "",
                                    "properties": {}
                                },
                                "value": "",
                                "workflowVariable": ""
                            }
                        },
                        {
                            "className": "org.joget.apps.form.lib.TextField",
                            "properties": {
                                "encryption": "",
                                "id": "incident_domain",
                                "label": "Incident Domain",
                                "maxlength": "",
                                "placeholder": "",
                                "readonly": "",
                                "readonlyLabel": "",
                                "size": "",
                                "storeNumeric": "",
                                "style": "",
                                "validator": {
                                    "className": "",
                                    "properties": {}
                                },
                                "value": "",
                                "workflowVariable": ""
                            }
                        },
                        {
                            "className": "org.joget.apps.form.lib.TextField",
                            "properties": {
                                "encryption": "",
                                "id": "longitude_gangguan",
                                "label": "Longitude Gangguan",
                                "maxlength": "",
                                "placeholder": "",
                                "readonly": "",
                                "readonlyLabel": "",
                                "size": "",
                                "storeNumeric": "",
                                "style": "",
                                "validator": {
                                    "className": "",
                                    "properties": {}
                                },
                                "value": "",
                                "workflowVariable": ""
                            }
                        },
                        {
                            "className": "org.joget.apps.form.lib.TextField",
                            "properties": {
                                "encryption": "",
                                "id": "latitude_gangguan",
                                "label": "Latitude Gangguan",
                                "maxlength": "",
                                "placeholder": "",
                                "readonly": "",
                                "readonlyLabel": "",
                                "size": "",
                                "storeNumeric": "",
                                "style": "",
                                "validator": {
                                    "className": "",
                                    "properties": {}
                                },
                                "value": "",
                                "workflowVariable": ""
                            }
                        }
                    ],
                    "properties": {"width": "32%"}
                },
                {
                    "className": "org.joget.apps.form.model.Column",
                    "elements": [{
                        "className": "org.joget.apps.form.lib.TextField",
                        "properties": {
                            "encryption": "",
                            "id": "region",
                            "label": "Region",
                            "maxlength": "",
                            "placeholder": "",
                            "readonly": "",
                            "readonlyLabel": "",
                            "size": "",
                            "storeNumeric": "",
                            "style": "",
                            "validator": {
                                "className": "",
                                "properties": {}
                            },
                            "value": "",
                            "workflowVariable": ""
                        }
                    }],
                    "properties": {"width": "32%"}
                },
                {
                    "className": "org.joget.apps.form.model.Column",
                    "elements": [{
                        "className": "org.joget.apps.form.lib.TextField",
                        "properties": {
                            "encryption": "",
                            "id": "status_actual_resolution",
                            "label": "Status Actual Resolution",
                            "maxlength": "",
                            "placeholder": "",
                            "readonly": "",
                            "readonlyLabel": "",
                            "size": "",
                            "storeNumeric": "",
                            "style": "",
                            "validator": {
                                "className": "",
                                "properties": {}
                            },
                            "value": "",
                            "workflowVariable": ""
                        }
                    }],
                    "properties": {"width": "32%"}
                }
            ],
            "properties": {
                "comment": "",
                "id": "section1",
                "join": "",
                "label": "Actual Resolution",
                "loadBinder": {
                    "className": "",
                    "properties": {}
                },
                "permission": {
                    "className": "",
                    "properties": {}
                },
                "permissionReadonly": "",
                "readonly": "",
                "readonlyLabel": "",
                "regex": "",
                "reverse": "",
                "storeBinder": {
                    "className": "",
                    "properties": {}
                },
                "visibilityControl": "",
                "visibilityValue": ""
            }
        },
        {
            "className": "org.joget.apps.form.model.Section",
            "elements": [
                {
                    "className": "org.joget.apps.form.model.Column",
                    "elements": [{
                        "className": "org.joget.apps.form.lib.TextField",
                        "properties": {
                            "encryption": "",
                            "id": "work_order",
                            "label": "Work Order",
                            "maxlength": "",
                            "placeholder": "",
                            "readonly": "",
                            "readonlyLabel": "",
                            "size": "",
                            "storeNumeric": "",
                            "style": "",
                            "validator": {
                                "className": "",
                                "properties": {}
                            },
                            "value": "",
                            "workflowVariable": ""
                        }
                    }],
                    "properties": {
                        "customWidth": "Workorder",
                        "horizontal": "",
                        "label": "",
                        "width": "Workorder"
                    }
                },
                {
                    "className": "org.joget.apps.form.model.Column",
                    "elements": [{
                        "className": "org.joget.apps.form.lib.TextField",
                        "properties": {
                            "encryption": "",
                            "id": "attribute_name",
                            "label": "Attribute Name",
                            "maxlength": "",
                            "placeholder": "",
                            "readonly": "",
                            "readonlyLabel": "",
                            "size": "",
                            "storeNumeric": "",
                            "style": "",
                            "validator": {
                                "className": "",
                                "properties": {}
                            },
                            "value": "",
                            "workflowVariable": ""
                        }
                    }],
                    "properties": {"width": ""}
                },
                {
                    "className": "org.joget.apps.form.model.Column",
                    "elements": [{
                        "className": "org.joget.apps.form.lib.TextField",
                        "properties": {
                            "encryption": "",
                            "id": "attribute_value",
                            "label": "Attribute Value",
                            "maxlength": "",
                            "placeholder": "",
                            "readonly": "",
                            "readonlyLabel": "",
                            "size": "",
                            "storeNumeric": "",
                            "style": "",
                            "validator": {
                                "className": "",
                                "properties": {}
                            },
                            "value": "",
                            "workflowVariable": ""
                        }
                    }],
                    "properties": {"width": ""}
                }
            ],
            "properties": {
                "comment": "",
                "id": "section2",
                "join": "",
                "label": "Workorder Attributs",
                "loadBinder": {
                    "className": "",
                    "properties": {}
                },
                "permission": {
                    "className": "",
                    "properties": {}
                },
                "permissionReadonly": "",
                "readonly": "",
                "readonlyLabel": "",
                "regex": "",
                "reverse": "",
                "storeBinder": {
                    "className": "",
                    "properties": {}
                },
                "visibilityControl": "",
                "visibilityValue": ""
            }
        },
        {
            "className": "org.joget.apps.form.model.Section",
            "elements": [{
                "className": "org.joget.apps.form.model.Column",
                "elements": [{
                    "className": "org.joget.plugin.enterprise.RichTextEditorField",
                    "properties": {
                        "editor": "",
                        "height": "",
                        "id": "resolution",
                        "label": "Resolution",
                        "mode": "",
                        "permissionType": "",
                        "placeholder": "",
                        "readonly": "",
                        "validator": {
                            "className": "",
                            "properties": {}
                        },
                        "value": ""
                    }
                }],
                "properties": {"width": "100%"}
            }],
            "properties": {
                "comment": "",
                "id": "section3",
                "join": "",
                "label": "",
                "loadBinder": {
                    "className": "",
                    "properties": {}
                },
                "permission": {
                    "className": "",
                    "properties": {}
                },
                "permissionReadonly": "",
                "readonly": "",
                "readonlyLabel": "",
                "regex": "",
                "reverse": "",
                "storeBinder": {
                    "className": "",
                    "properties": {}
                },
                "visibilityControl": "",
                "visibilityValue": ""
            }
        },
        {
            "className": "org.joget.apps.form.model.Section",
            "elements": [{
                "className": "org.joget.apps.form.model.Column",
                "elements": [
                    {
                        "className": "org.joget.plugin.enterprise.AdvancedGrid",
                        "properties": {
                            "deleteMessage": "Delete row?",
                            "disabledAdd": "false",
                            "disabledDelete": "false",
                            "errorMessage": "Invalid number of rows",
                            "hint": "Click to edit. Tab to save.",
                            "id": "field13",
                            "keyToSave": "9",
                            "label": "Advanced Grid",
                            "pagingOptions": "10,20,50,100",
                            "readonly": "False",
                            "recordPerPage": "20",
                            "search": "False",
                            "showRowNumber": "true"
                        }
                    },
                    {
                        "className": "org.joget.apps.form.lib.FileUpload",
                        "properties": {
                            "attachment": "",
                            "fileType": "",
                            "fileTypeMsg": "Invalid file type",
                            "id": "document",
                            "label": "Document",
                            "maxSize": "",
                            "maxSizeMsg": "File size limit exceeded",
                            "multiple": "",
                            "padding": "",
                            "permissionType": "",
                            "readonly": "",
                            "removeFile": "",
                            "resizeHeight": "",
                            "resizeMethod": "",
                            "resizeQuality": "0.8",
                            "resizeWidth": "",
                            "size": "",
                            "validator": {
                                "className": "",
                                "properties": {}
                            }
                        }
                    }
                ],
                "properties": {"width": "100%"}
            }],
            "properties": {
                "comment": "",
                "id": "section4",
                "join": "",
                "label": "Attachments",
                "loadBinder": {
                    "className": "",
                    "properties": {}
                },
                "permission": {
                    "className": "",
                    "properties": {}
                },
                "permissionReadonly": "",
                "readonly": "",
                "readonlyLabel": "",
                "regex": "",
                "reverse": "",
                "storeBinder": {
                    "className": "",
                    "properties": {}
                },
                "visibilityControl": "",
                "visibilityValue": ""
            }
        }
    ],
    "properties": {
        "description": "",
        "id": "actualResolution",
        "loadBinder": {
            "className": "org.joget.apps.form.lib.WorkflowFormBinder",
            "properties": {}
        },
        "name": "T03-Actual Resolution",
        "noPermissionMessage": "",
        "permission": {
            "className": "",
            "properties": {}
        },
        "postProcessor": {
            "className": "",
            "properties": {}
        },
        "postProcessorRunOn": "create",
        "storeBinder": {
            "className": "org.joget.apps.form.lib.WorkflowFormBinder",
            "properties": {}
        },
        "tableName": "ticket"
    }
}